{
  "type": "node--health_care_region_page",
  "id": "17bfe247-9df5-4217-a48a-973f8676d6e4",
  "drupal_internal__nid": 8525,
  "drupal_internal__vid": 763943,
  "langcode": "en",
  "revision_timestamp": "2023-04-13T18:17:36+00:00",
  "revision_log": "revised Medical Records Office link - CMS Helpdesk",
  "status": true,
  "title": "VA New York Harbor health care",
  "created": "2020-10-19T20:31:40+00:00",
  "changed": "2023-04-13T18:17:36+00:00",
  "promote": false,
  "sticky": false,
  "default_langcode": true,
  "revision_translation_affected": true,
  "breadcrumbs": [
    {
      "uri": "https://content-build-medc0xjkxm4jmpzxl3tfbcs7qcddsivh.ci.cms.va.gov/",
      "title": "Home",
      "options": []
    },
    {
      "uri": "internal:#",
      "title": "VA New York Harbor health care",
      "options": []
    }
  ],
  "moderation_state": "published",
  "expiration_date": null,
  "warning_date": null,
  "metatag": [
    {
      "tag": "meta",
      "attributes": {
        "name": "title",
        "content": "VA New York Harbor health care | Veterans Affairs"
      }
    },
    {
      "tag": "meta",
      "attributes": {
        "name": "description",
        "content": "At VA New York Harbor Healthcare System, our health care teams are deeply experienced and guided by the needs of Veterans, their families, and caregivers. Find a health facility near you, and manage your health online. Sign up for community events and updates."
      }
    },
    {
      "tag": "link",
      "attributes": {
        "rel": "image_src",
        "href": "https://www.va.gov/img/design/logo/va-og-image.png"
      }
    },
    {
      "tag": "meta",
      "attributes": {
        "property": "og:site_name",
        "content": "Veterans Affairs"
      }
    },
    {
      "tag": "meta",
      "attributes": {
        "property": "og:title",
        "content": "VA New York Harbor health care | Veterans Affairs"
      }
    },
    {
      "tag": "meta",
      "attributes": {
        "property": "og:description",
        "content": "At VA New York Harbor Healthcare System, our health care teams are deeply experienced and guided by the needs of Veterans, their families, and caregivers. Find a health facility near you, and manage your health online. Sign up for community events and updates."
      }
    },
    {
      "tag": "meta",
      "attributes": {
        "property": "og:image",
        "content": "https://dsva-vagov-staging-cms-files.s3.us-gov-west-1.amazonaws.com/styles/3_2_medium_thumbnail/public/2020-10/manhattanCampus1024x960.jpg"
      }
    },
    {
      "tag": "meta",
      "attributes": {
        "property": "og:image:alt",
        "content": "Manhattan Veterans Administration Medical Center"
      }
    },
    {
      "tag": "meta",
      "attributes": {
        "name": "twitter:card",
        "content": "summary_large_image"
      }
    },
    {
      "tag": "meta",
      "attributes": {
        "name": "twitter:site",
        "content": "@DeptVetAffairs"
      }
    },
    {
      "tag": "meta",
      "attributes": {
        "name": "twitter:title",
        "content": "VA New York Harbor health care | Veterans Affairs"
      }
    },
    {
      "tag": "meta",
      "attributes": {
        "name": "twitter:description",
        "content": "At VA New York Harbor Healthcare System, our health care teams are deeply experienced and guided by the needs of Veterans, their families, and caregivers. Find a health facility near you, and manage your health online. Sign up for community events and updates."
      }
    },
    {
      "tag": "meta",
      "attributes": {
        "name": "twitter:image:alt",
        "content": "Manhattan Veterans Administration Medical Center"
      }
    },
    {
      "tag": "meta",
      "attributes": {
        "name": "twitter:image",
        "content": "https://dsva-vagov-staging-cms-files.s3.us-gov-west-1.amazonaws.com/styles/3_2_medium_thumbnail/public/2020-10/manhattanCampus1024x960.jpg"
      }
    }
  ],
  "path": {
    "alias": "/new-york-harbor-health-care",
    "pid": 10082,
    "langcode": "en"
  },
  "content_translation_source": "und",
  "content_translation_outdated": false,
  "field_appointments_online": false,
  "field_description": "At VA New York Harbor Healthcare System, our health care teams are deeply experienced and guided by the needs of Veterans, their families, and caregivers. Find a health facility near you, and manage your health online. Sign up for community events and updates.",
  "field_facebook": {
    "uri": "https://www.facebook.com/VANYHarbor",
    "title": "The New York Harbor Healthcare System Facebook page",
    "options": [],
    "url": "https://www.facebook.com/VANYHarbor"
  },
  "field_flickr": {
    "uri": "https://www.flickr.com/photos/144760790@N02/albums",
    "title": "The New York Harbor Healthcare System",
    "options": [],
    "url": "https://www.flickr.com/photos/144760790@N02/albums"
  },
  "field_govdelivery_id_emerg": "USVHA_387",
  "field_govdelivery_id_news": "USVHA_145",
  "field_instagram": null,
  "field_intro_text": "At VA New York Harbor Healthcare System, our health care teams are deeply experienced and guided by the needs of Veterans, their families, and caregivers. Find a health facility near you, and manage your health online. Sign up for community events and updates.",
  "field_last_saved_by_an_editor": "2023-04-13T18:17:37+00:00",
  "field_meta_tags": null,
  "field_operating_status": {
    "uri": "entity:node/8526",
    "title": "Operating status - VA New York Harbor health care",
    "options": [],
    "url": "/new-york-harbor-health-care/operating-status"
  },
  "field_other_va_locations": ["vc_0133V", "vc_0105V", "vc_0106V"],
  "field_twitter": {
    "uri": "https://twitter.com/VANYHarbor",
    "title": "The New York Harbor Healthcare System",
    "options": [],
    "url": "https://twitter.com/VANYHarbor"
  },
  "field_vamc_ehr_system": "vista",
  "field_vamc_system_official_name": "VA New York Harbor Healthcare System",
  "field_va_health_connect_phone": "800-877-6976",
  "field_youtube": null,
  "links": {
    "self": {
      "href": "https://content-build-medc0xjkxm4jmpzxl3tfbcs7qcddsivh.ci.cms.va.gov/jsonapi/node/health_care_region_page/17bfe247-9df5-4217-a48a-973f8676d6e4?resourceVersion=id%3A763943"
    }
  },
  "node_type": {
    "type": "node_type--node_type",
    "id": "d611ade3-cc27-4359-8af1-6fba3384200f",
    "resourceIdObjMeta": {
      "drupal_internal__target_id": "health_care_region_page"
    }
  },
  "revision_uid": {
    "type": "user--user",
    "id": "f687120a-7fbd-429e-a9c0-4b287ce0df37",
    "resourceIdObjMeta": {
      "drupal_internal__target_id": 4201
    }
  },
  "uid": {
    "type": "user--user",
    "id": "42b77c61-aabd-4182-8a0e-2d19f0267eff",
    "resourceIdObjMeta": {
      "drupal_internal__target_id": 1270
    }
  },
  "field_administration": {
    "type": "taxonomy_term--administration",
    "id": "5c2e2742-4432-47b7-a540-b486e1d2a058",
    "drupal_internal__tid": 254,
    "drupal_internal__revision_id": 2334,
    "langcode": "en",
    "revision_created": "2024-08-13T20:05:29+00:00",
    "revision_log_message": null,
    "status": true,
    "name": "VA New York Harbor health care",
    "description": null,
    "weight": 5,
    "changed": "2024-08-13T20:05:29+00:00",
    "default_langcode": true,
    "revision_translation_affected": true,
    "breadcrumbs": [
      {
        "uri": "https://content-build-medc0xjkxm4jmpzxl3tfbcs7qcddsivh.ci.cms.va.gov/",
        "title": "Home",
        "options": []
      },
      {
        "uri": "https://content-build-medc0xjkxm4jmpzxl3tfbcs7qcddsivh.ci.cms.va.gov/section/vha",
        "title": "VHA",
        "options": []
      },
      {
        "uri": "https://content-build-medc0xjkxm4jmpzxl3tfbcs7qcddsivh.ci.cms.va.gov/section/vamc-facilities",
        "title": "VAMC facilities",
        "options": []
      },
      {
        "uri": "https://content-build-medc0xjkxm4jmpzxl3tfbcs7qcddsivh.ci.cms.va.gov/section/vha/visn-2",
        "title": "VISN 2",
        "options": []
      },
      {
        "uri": "internal:#",
        "title": "VA New York Harbor health care",
        "options": []
      }
    ],
    "moderation_state": null,
    "metatag": [
      {
        "tag": "meta",
        "attributes": {
          "name": "title",
          "content": "VA New York Harbor health care | VA.gov CMS"
        }
      },
      {
        "tag": "link",
        "attributes": {
          "rel": "canonical",
          "href": "https://content-build-medc0xjkxm4jmpzxl3tfbcs7qcddsivh.ci.cms.va.gov/section/vha/vamc-facilities/va-new-york-harbor-health-care"
        }
      }
    ],
    "path": {
      "alias": "/section/vha/vamc-facilities/va-new-york-harbor-health-care",
      "pid": 8065,
      "langcode": "en"
    },
    "content_translation_source": "und",
    "content_translation_outdated": false,
    "content_translation_created": null,
    "field_description": null,
    "links": {
      "self": {
        "href": "https://content-build-medc0xjkxm4jmpzxl3tfbcs7qcddsivh.ci.cms.va.gov/jsonapi/taxonomy_term/administration/5c2e2742-4432-47b7-a540-b486e1d2a058?resourceVersion=id%3A2334"
      }
    },
    "resourceIdObjMeta": {
      "drupal_internal__target_id": 254
    },
    "vid": {
      "type": "taxonomy_vocabulary--taxonomy_vocabulary",
      "id": "645055c5-e567-4683-b6db-459ce04522ce",
      "resourceIdObjMeta": {
        "drupal_internal__target_id": "administration"
      }
    },
    "revision_user": {
      "type": "user--user",
      "id": "3ad0956c-0561-4c79-a25c-b6bf3a6fe05c",
      "resourceIdObjMeta": {
        "drupal_internal__target_id": 4942
      }
    },
    "parent": [
      {
        "type": "taxonomy_term--administration",
        "id": "774dbf64-ad5a-4f9f-9744-7169e9e1786c",
        "resourceIdObjMeta": {
          "drupal_internal__target_id": 163
        }
      }
    ],
    "content_translation_uid": null,
    "field_product": {
      "type": "taxonomy_term--products",
      "id": "2fe1cb98-c03e-49fe-bb09-d73b66b99c8d",
      "resourceIdObjMeta": {
        "drupal_internal__target_id": 284
      }
    },
    "relationshipNames": [
      "vid",
      "revision_user",
      "parent",
      "content_translation_uid",
      "field_product"
    ]
  },
  "field_clinical_health_services": ["Mock data omitted"],
  "field_media": {
    "type": "media--image",
    "id": "6c6e365c-e9ca-4ec1-9f87-1b686d7defe7",
    "drupal_internal__mid": 1545,
    "drupal_internal__vid": 1719,
    "status": true,
    "name": "manhattanCampus1024x960.jpg",
    "created": "2020-10-19T20:34:32+00:00",
    "changed": "2020-10-19T20:34:32+00:00",
    "breadcrumbs": [
      {
        "uri": "https://content-build-medc0xjkxm4jmpzxl3tfbcs7qcddsivh.ci.cms.va.gov/",
        "title": "Home",
        "options": []
      },
      {
        "uri": "https://content-build-medc0xjkxm4jmpzxl3tfbcs7qcddsivh.ci.cms.va.gov/media/1545",
        "title": "ManhattanCampus1024x960.jpg",
        "options": []
      }
    ],
    "langcode": "this isn't in the real data, but it'll make TypeScript happy",
    "path": {
      "alias": null,
      "pid": null,
      "langcode": "en"
    },
    "field_description": "Manhattan Veterans Administration Medical Center",
    "links": {
      "self": {
        "href": "https://content-build-medc0xjkxm4jmpzxl3tfbcs7qcddsivh.ci.cms.va.gov/jsonapi/media/image/6c6e365c-e9ca-4ec1-9f87-1b686d7defe7?resourceVersion=id%3A1719"
      }
    },
    "resourceIdObjMeta": {
      "drupal_internal__target_id": 1545
    },
    "bundle": {
      "type": "media_type--media_type",
      "id": "92f64a34-81e5-4094-82a9-4fe61d7f2227",
      "resourceIdObjMeta": {
        "drupal_internal__target_id": "image"
      }
    },
    "uid": {
      "type": "user--user",
      "id": "42b77c61-aabd-4182-8a0e-2d19f0267eff",
      "resourceIdObjMeta": {
        "drupal_internal__target_id": 1270
      }
    },
    "thumbnail": {
      "type": "file--file",
      "id": "23564949-4f47-42fc-8e0f-92b4cd84578e",
      "drupal_internal__fid": 1753,
      "langcode": "en",
      "filename": "manhattanCampus1024x960.jpg",
      "uri": {
        "value": "public://2020-10/manhattanCampus1024x960.jpg",
        "url": "https://dsva-vagov-staging-cms-files.s3.us-gov-west-1.amazonaws.com/2020-10/manhattanCampus1024x960.jpg"
      },
      "filemime": "image/jpeg",
      "filesize": 15529,
      "status": true,
      "created": "2020-10-19T20:34:32+00:00",
      "changed": "2020-10-19T20:35:16+00:00",
      "breadcrumbs": [],
      "links": {
        "1_1_square_medium_thumbnail": {
          "href": "https://dsva-vagov-staging-cms-files.s3.us-gov-west-1.amazonaws.com/styles/1_1_square_medium_thumbnail/public/2020-10/manhattanCampus1024x960.jpg",
          "meta": {
            "linkParams": {
              "width": "240",
              "rel": [
                "drupal://jsonapi/extensions/consumer_image_styles/links/relation-types/#derivative"
              ]
            },
            "rel": [
              "drupal://jsonapi/extensions/consumer_image_styles/links/relation-types/#derivative"
            ]
          }
        },
        "2_1_large": {
          "href": "https://dsva-vagov-staging-cms-files.s3.us-gov-west-1.amazonaws.com/styles/2_1_large/public/2020-10/manhattanCampus1024x960.jpg",
          "meta": {
            "linkParams": {
              "width": "512",
              "rel": [
                "drupal://jsonapi/extensions/consumer_image_styles/links/relation-types/#derivative"
              ]
            },
            "rel": [
              "drupal://jsonapi/extensions/consumer_image_styles/links/relation-types/#derivative"
            ]
          }
        },
        "2_1_medium_thumbnail": {
          "href": "https://dsva-vagov-staging-cms-files.s3.us-gov-west-1.amazonaws.com/styles/2_1_medium_thumbnail/public/2020-10/manhattanCampus1024x960.jpg",
          "meta": {
            "linkParams": {
              "width": "240",
              "rel": [
                "drupal://jsonapi/extensions/consumer_image_styles/links/relation-types/#derivative"
              ]
            },
            "rel": [
              "drupal://jsonapi/extensions/consumer_image_styles/links/relation-types/#derivative"
            ]
          }
        },
        "2_3_medium_thumbnail": {
          "href": "https://dsva-vagov-staging-cms-files.s3.us-gov-west-1.amazonaws.com/styles/2_3_medium_thumbnail/public/2020-10/manhattanCampus1024x960.jpg",
          "meta": {
            "linkParams": {
              "width": "480",
              "rel": [
                "drupal://jsonapi/extensions/consumer_image_styles/links/relation-types/#derivative"
              ]
            },
            "rel": [
              "drupal://jsonapi/extensions/consumer_image_styles/links/relation-types/#derivative"
            ]
          }
        },
        "3_2_medium_thumbnail": {
          "href": "https://dsva-vagov-staging-cms-files.s3.us-gov-west-1.amazonaws.com/styles/3_2_medium_thumbnail/public/2020-10/manhattanCampus1024x960.jpg",
          "meta": {
            "linkParams": {
              "width": "320",
              "rel": [
                "drupal://jsonapi/extensions/consumer_image_styles/links/relation-types/#derivative"
              ]
            },
            "rel": [
              "drupal://jsonapi/extensions/consumer_image_styles/links/relation-types/#derivative"
            ]
          }
        },
        "7_2_medium_thumbnail": {
          "href": "https://dsva-vagov-staging-cms-files.s3.us-gov-west-1.amazonaws.com/styles/7_2_medium_thumbnail/public/2020-10/manhattanCampus1024x960.jpg",
          "meta": {
            "linkParams": {
              "width": "300",
              "rel": [
                "drupal://jsonapi/extensions/consumer_image_styles/links/relation-types/#derivative"
              ]
            },
            "rel": [
              "drupal://jsonapi/extensions/consumer_image_styles/links/relation-types/#derivative"
            ]
          }
        },
        "full_content_width": {
          "href": "https://dsva-vagov-staging-cms-files.s3.us-gov-west-1.amazonaws.com/styles/full_content_width/public/2020-10/manhattanCampus1024x960.jpg",
          "meta": {
            "linkParams": {
              "width": "180",
              "rel": [
                "drupal://jsonapi/extensions/consumer_image_styles/links/relation-types/#derivative"
              ]
            },
            "rel": [
              "drupal://jsonapi/extensions/consumer_image_styles/links/relation-types/#derivative"
            ]
          }
        },
        "large": {
          "href": "https://dsva-vagov-staging-cms-files.s3.us-gov-west-1.amazonaws.com/styles/large/public/2020-10/manhattanCampus1024x960.jpg",
          "meta": {
            "linkParams": {
              "width": "180",
              "rel": [
                "drupal://jsonapi/extensions/consumer_image_styles/links/relation-types/#derivative"
              ]
            },
            "rel": [
              "drupal://jsonapi/extensions/consumer_image_styles/links/relation-types/#derivative"
            ]
          }
        },
        "original": {
          "href": "https://dsva-vagov-staging-cms-files.s3.us-gov-west-1.amazonaws.com/styles/original/public/2020-10/manhattanCampus1024x960.jpg",
          "meta": {
            "linkParams": {
              "width": "180",
              "rel": [
                "drupal://jsonapi/extensions/consumer_image_styles/links/relation-types/#derivative"
              ]
            },
            "rel": [
              "drupal://jsonapi/extensions/consumer_image_styles/links/relation-types/#derivative"
            ]
          }
        },
        "self": {
          "href": "https://content-build-medc0xjkxm4jmpzxl3tfbcs7qcddsivh.ci.cms.va.gov/jsonapi/file/file/23564949-4f47-42fc-8e0f-92b4cd84578e"
        },
        "viewport_width": {
          "href": "https://dsva-vagov-staging-cms-files.s3.us-gov-west-1.amazonaws.com/styles/viewport_width/public/2020-10/manhattanCampus1024x960.jpg",
          "meta": {
            "linkParams": {
              "width": "180",
              "rel": [
                "drupal://jsonapi/extensions/consumer_image_styles/links/relation-types/#derivative"
              ]
            },
            "rel": [
              "drupal://jsonapi/extensions/consumer_image_styles/links/relation-types/#derivative"
            ]
          }
        }
      },
      "resourceIdObjMeta": {
        "alt": "Manhattan Veterans Administration Medical Center",
        "title": null,
        "width": 259,
        "height": 180,
        "drupal_internal__target_id": 1753
      },
      "uid": {
        "type": "user--user",
        "id": "42b77c61-aabd-4182-8a0e-2d19f0267eff",
        "resourceIdObjMeta": {
          "drupal_internal__target_id": 1270
        }
      },
      "relationshipNames": ["uid"]
    },
    "image": {
      "type": "file--file",
      "id": "23564949-4f47-42fc-8e0f-92b4cd84578e",
      "drupal_internal__fid": 1753,
      "langcode": "en",
      "filename": "manhattanCampus1024x960.jpg",
      "uri": {
        "value": "public://2020-10/manhattanCampus1024x960.jpg",
        "url": "https://dsva-vagov-staging-cms-files.s3.us-gov-west-1.amazonaws.com/2020-10/manhattanCampus1024x960.jpg"
      },
      "filemime": "image/jpeg",
      "filesize": 15529,
      "status": true,
      "created": "2020-10-19T20:34:32+00:00",
      "changed": "2020-10-19T20:35:16+00:00",
      "breadcrumbs": [],
      "links": {
        "1_1_square_medium_thumbnail": {
          "href": "https://dsva-vagov-staging-cms-files.s3.us-gov-west-1.amazonaws.com/styles/1_1_square_medium_thumbnail/public/2020-10/manhattanCampus1024x960.jpg",
          "meta": {
            "linkParams": {
              "width": "240",
              "rel": [
                "drupal://jsonapi/extensions/consumer_image_styles/links/relation-types/#derivative"
              ]
            },
            "rel": [
              "drupal://jsonapi/extensions/consumer_image_styles/links/relation-types/#derivative"
            ]
          }
        },
        "2_1_large": {
          "href": "https://dsva-vagov-staging-cms-files.s3.us-gov-west-1.amazonaws.com/styles/2_1_large/public/2020-10/manhattanCampus1024x960.jpg",
          "meta": {
            "linkParams": {
              "width": "512",
              "rel": [
                "drupal://jsonapi/extensions/consumer_image_styles/links/relation-types/#derivative"
              ]
            },
            "rel": [
              "drupal://jsonapi/extensions/consumer_image_styles/links/relation-types/#derivative"
            ]
          }
        },
        "2_1_medium_thumbnail": {
          "href": "https://dsva-vagov-staging-cms-files.s3.us-gov-west-1.amazonaws.com/styles/2_1_medium_thumbnail/public/2020-10/manhattanCampus1024x960.jpg",
          "meta": {
            "linkParams": {
              "width": "240",
              "rel": [
                "drupal://jsonapi/extensions/consumer_image_styles/links/relation-types/#derivative"
              ]
            },
            "rel": [
              "drupal://jsonapi/extensions/consumer_image_styles/links/relation-types/#derivative"
            ]
          }
        },
        "2_3_medium_thumbnail": {
          "href": "https://dsva-vagov-staging-cms-files.s3.us-gov-west-1.amazonaws.com/styles/2_3_medium_thumbnail/public/2020-10/manhattanCampus1024x960.jpg",
          "meta": {
            "linkParams": {
              "width": "480",
              "rel": [
                "drupal://jsonapi/extensions/consumer_image_styles/links/relation-types/#derivative"
              ]
            },
            "rel": [
              "drupal://jsonapi/extensions/consumer_image_styles/links/relation-types/#derivative"
            ]
          }
        },
        "3_2_medium_thumbnail": {
          "href": "https://dsva-vagov-staging-cms-files.s3.us-gov-west-1.amazonaws.com/styles/3_2_medium_thumbnail/public/2020-10/manhattanCampus1024x960.jpg",
          "meta": {
            "linkParams": {
              "width": "320",
              "rel": [
                "drupal://jsonapi/extensions/consumer_image_styles/links/relation-types/#derivative"
              ]
            },
            "rel": [
              "drupal://jsonapi/extensions/consumer_image_styles/links/relation-types/#derivative"
            ]
          }
        },
        "7_2_medium_thumbnail": {
          "href": "https://dsva-vagov-staging-cms-files.s3.us-gov-west-1.amazonaws.com/styles/7_2_medium_thumbnail/public/2020-10/manhattanCampus1024x960.jpg",
          "meta": {
            "linkParams": {
              "width": "300",
              "rel": [
                "drupal://jsonapi/extensions/consumer_image_styles/links/relation-types/#derivative"
              ]
            },
            "rel": [
              "drupal://jsonapi/extensions/consumer_image_styles/links/relation-types/#derivative"
            ]
          }
        },
        "full_content_width": {
          "href": "https://dsva-vagov-staging-cms-files.s3.us-gov-west-1.amazonaws.com/styles/full_content_width/public/2020-10/manhattanCampus1024x960.jpg",
          "meta": {
            "linkParams": {
              "width": "180",
              "rel": [
                "drupal://jsonapi/extensions/consumer_image_styles/links/relation-types/#derivative"
              ]
            },
            "rel": [
              "drupal://jsonapi/extensions/consumer_image_styles/links/relation-types/#derivative"
            ]
          }
        },
        "large": {
          "href": "https://dsva-vagov-staging-cms-files.s3.us-gov-west-1.amazonaws.com/styles/large/public/2020-10/manhattanCampus1024x960.jpg",
          "meta": {
            "linkParams": {
              "width": "180",
              "rel": [
                "drupal://jsonapi/extensions/consumer_image_styles/links/relation-types/#derivative"
              ]
            },
            "rel": [
              "drupal://jsonapi/extensions/consumer_image_styles/links/relation-types/#derivative"
            ]
          }
        },
        "original": {
          "href": "https://dsva-vagov-staging-cms-files.s3.us-gov-west-1.amazonaws.com/styles/original/public/2020-10/manhattanCampus1024x960.jpg",
          "meta": {
            "linkParams": {
              "width": "180",
              "rel": [
                "drupal://jsonapi/extensions/consumer_image_styles/links/relation-types/#derivative"
              ]
            },
            "rel": [
              "drupal://jsonapi/extensions/consumer_image_styles/links/relation-types/#derivative"
            ]
          }
        },
        "self": {
          "href": "https://content-build-medc0xjkxm4jmpzxl3tfbcs7qcddsivh.ci.cms.va.gov/jsonapi/file/file/23564949-4f47-42fc-8e0f-92b4cd84578e"
        },
        "viewport_width": {
          "href": "https://dsva-vagov-staging-cms-files.s3.us-gov-west-1.amazonaws.com/styles/viewport_width/public/2020-10/manhattanCampus1024x960.jpg",
          "meta": {
            "linkParams": {
              "width": "180",
              "rel": [
                "drupal://jsonapi/extensions/consumer_image_styles/links/relation-types/#derivative"
              ]
            },
            "rel": [
              "drupal://jsonapi/extensions/consumer_image_styles/links/relation-types/#derivative"
            ]
          }
        }
      },
      "resourceIdObjMeta": {
        "alt": "Manhattan Veterans Administration Medical Center",
        "title": "",
        "width": 259,
        "height": 180,
        "drupal_internal__target_id": 1753
      },
      "uid": {
        "type": "user--user",
        "id": "42b77c61-aabd-4182-8a0e-2d19f0267eff",
        "resourceIdObjMeta": {
          "drupal_internal__target_id": 1270
        }
      },
      "relationshipNames": ["uid"]
    },
    "relationshipNames": ["bundle", "uid", "thumbnail", "image"]
  },
  "field_related_links": {
    "type": "paragraph--list_of_link_teasers",
    "id": "8fee84a4-d821-4a90-ab51-25971100c481",
    "drupal_internal__id": 13881,
    "drupal_internal__revision_id": 923261,
    "langcode": "en",
    "status": true,
    "created": "2020-10-19T20:31:40+00:00",
    "parent_id": "8525",
    "parent_type": "node",
    "parent_field_name": "field_related_links",
    "behavior_settings": [],
    "default_langcode": true,
    "revision_translation_affected": true,
    "breadcrumbs": [],
    "content_translation_source": "und",
    "content_translation_outdated": false,
    "content_translation_changed": null,
    "field_title": "In the spotlight at VA New York Harbor health care",
    "links": {
      "self": {
        "href": "https://content-build-medc0xjkxm4jmpzxl3tfbcs7qcddsivh.ci.cms.va.gov/jsonapi/paragraph/list_of_link_teasers/8fee84a4-d821-4a90-ab51-25971100c481?resourceVersion=id%3A923261"
      }
    },
    "resourceIdObjMeta": {
      "target_revision_id": 923261,
      "drupal_internal__target_id": 13881
    },
    "paragraph_type": {
      "type": "paragraphs_type--paragraphs_type",
      "id": "17be725c-343b-4050-a3c0-4e953226233e",
      "resourceIdObjMeta": {
        "drupal_internal__target_id": "list_of_link_teasers"
      }
    },
    "field_va_paragraphs": [
      {
        "type": "paragraph--link_teaser",
        "id": "67ec0aee-d964-4e83-805f-2a133824c15c",
        "drupal_internal__id": 13880,
        "drupal_internal__revision_id": 923254,
        "langcode": "en",
        "status": true,
        "created": "2020-10-19T20:31:40+00:00",
        "parent_id": "13881",
        "parent_type": "paragraph",
        "parent_field_name": "field_va_paragraphs",
        "behavior_settings": [],
        "default_langcode": true,
        "revision_translation_affected": true,
        "breadcrumbs": [],
        "content_translation_source": "und",
        "content_translation_outdated": false,
        "content_translation_changed": null,
        "field_link": {
          "uri": "entity:node/9417",
          "title": "Get help from a patient advocate",
          "options": [],
          "url": "/new-york-harbor-health-care/health-services/patient-advocates"
        },
        "field_link_summary": null,
        "links": {
          "self": {
            "href": "https://content-build-medc0xjkxm4jmpzxl3tfbcs7qcddsivh.ci.cms.va.gov/jsonapi/paragraph/link_teaser/67ec0aee-d964-4e83-805f-2a133824c15c?resourceVersion=id%3A923254"
          }
        },
        "resourceIdObjMeta": {
          "target_revision_id": 923254,
          "drupal_internal__target_id": 13880
        },
        "paragraph_type": {
          "type": "paragraphs_type--paragraphs_type",
          "id": "072db7a4-476e-41a6-ab49-c44184281451",
          "resourceIdObjMeta": {
            "drupal_internal__target_id": "link_teaser"
          }
        },
        "relationshipNames": ["paragraph_type"]
      },
      {
        "type": "paragraph--link_teaser",
        "id": "ce9da3d6-c49d-4370-9493-9628bfa462d6",
        "drupal_internal__id": 30078,
        "drupal_internal__revision_id": 923255,
        "langcode": "en",
        "status": true,
        "created": "2021-03-02T14:33:44+00:00",
        "parent_id": "13881",
        "parent_type": "paragraph",
        "parent_field_name": "field_va_paragraphs",
        "behavior_settings": [],
        "default_langcode": true,
        "revision_translation_affected": true,
        "breadcrumbs": [],
        "content_translation_source": "und",
        "content_translation_outdated": false,
        "content_translation_changed": null,
        "field_link": {
          "uri": "entity:node/45723",
          "title": "Access your health records",
          "options": [],
          "url": "/new-york-harbor-health-care/medical-records-office"
        },
        "field_link_summary": null,
        "links": {
          "self": {
            "href": "https://content-build-medc0xjkxm4jmpzxl3tfbcs7qcddsivh.ci.cms.va.gov/jsonapi/paragraph/link_teaser/ce9da3d6-c49d-4370-9493-9628bfa462d6?resourceVersion=id%3A923255"
          }
        },
        "resourceIdObjMeta": {
          "target_revision_id": 923255,
          "drupal_internal__target_id": 30078
        },
        "paragraph_type": {
          "type": "paragraphs_type--paragraphs_type",
          "id": "072db7a4-476e-41a6-ab49-c44184281451",
          "resourceIdObjMeta": {
            "drupal_internal__target_id": "link_teaser"
          }
        },
        "relationshipNames": ["paragraph_type"]
      },
      {
        "type": "paragraph--link_teaser",
        "id": "e21ee8f3-d4c3-4c08-ba6f-b2a9ec1df35f",
        "drupal_internal__id": 30079,
        "drupal_internal__revision_id": 923256,
        "langcode": "en",
        "status": true,
        "created": "2021-03-02T14:34:50+00:00",
        "parent_id": "13881",
        "parent_type": "paragraph",
        "parent_field_name": "field_va_paragraphs",
        "behavior_settings": [],
        "default_langcode": true,
        "revision_translation_affected": true,
        "breadcrumbs": [],
        "content_translation_source": "und",
        "content_translation_outdated": false,
        "content_translation_changed": null,
        "field_link": {
          "uri": "entity:node/9441",
          "title": "Find a phone number",
          "options": [],
          "url": "/new-york-harbor-health-care/contact-us"
        },
        "field_link_summary": null,
        "links": {
          "self": {
            "href": "https://content-build-medc0xjkxm4jmpzxl3tfbcs7qcddsivh.ci.cms.va.gov/jsonapi/paragraph/link_teaser/e21ee8f3-d4c3-4c08-ba6f-b2a9ec1df35f?resourceVersion=id%3A923256"
          }
        },
        "resourceIdObjMeta": {
          "target_revision_id": 923256,
          "drupal_internal__target_id": 30079
        },
        "paragraph_type": {
          "type": "paragraphs_type--paragraphs_type",
          "id": "072db7a4-476e-41a6-ab49-c44184281451",
          "resourceIdObjMeta": {
            "drupal_internal__target_id": "link_teaser"
          }
        },
        "relationshipNames": ["paragraph_type"]
      },
      {
        "type": "paragraph--link_teaser",
        "id": "752edbd1-0f5a-45a1-9b12-cfef9be7e62b",
        "drupal_internal__id": 30080,
        "drupal_internal__revision_id": 923257,
        "langcode": "en",
        "status": true,
        "created": "2021-03-02T14:35:03+00:00",
        "parent_id": "13881",
        "parent_type": "paragraph",
        "parent_field_name": "field_va_paragraphs",
        "behavior_settings": [],
        "default_langcode": true,
        "revision_translation_affected": true,
        "breadcrumbs": [],
        "content_translation_source": "und",
        "content_translation_outdated": false,
        "content_translation_changed": null,
        "field_link": {
          "uri": "entity:node/45597",
          "title": "Check your billing, insurance, and payment options",
          "options": [],
          "url": "/new-york-harbor-health-care/billing-and-insurance"
        },
        "field_link_summary": null,
        "links": {
          "self": {
            "href": "https://content-build-medc0xjkxm4jmpzxl3tfbcs7qcddsivh.ci.cms.va.gov/jsonapi/paragraph/link_teaser/752edbd1-0f5a-45a1-9b12-cfef9be7e62b?resourceVersion=id%3A923257"
          }
        },
        "resourceIdObjMeta": {
          "target_revision_id": 923257,
          "drupal_internal__target_id": 30080
        },
        "paragraph_type": {
          "type": "paragraphs_type--paragraphs_type",
          "id": "072db7a4-476e-41a6-ab49-c44184281451",
          "resourceIdObjMeta": {
            "drupal_internal__target_id": "link_teaser"
          }
        },
        "relationshipNames": ["paragraph_type"]
      },
      {
        "type": "paragraph--link_teaser",
        "id": "f680869b-16f1-4507-a7a5-c30c41c9eaed",
        "drupal_internal__id": 30081,
        "drupal_internal__revision_id": 923258,
        "langcode": "en",
        "status": true,
        "created": "2021-03-02T14:35:53+00:00",
        "parent_id": "13881",
        "parent_type": "paragraph",
        "parent_field_name": "field_va_paragraphs",
        "behavior_settings": [],
        "default_langcode": true,
        "revision_translation_affected": true,
        "breadcrumbs": [],
        "content_translation_source": "und",
        "content_translation_outdated": false,
        "content_translation_changed": null,
        "field_link": {
          "uri": "entity:node/9430",
          "title": "Volunteer or donate",
          "options": [],
          "url": "/new-york-harbor-health-care/work-with-us/volunteer-or-donate"
        },
        "field_link_summary": null,
        "links": {
          "self": {
            "href": "https://content-build-medc0xjkxm4jmpzxl3tfbcs7qcddsivh.ci.cms.va.gov/jsonapi/paragraph/link_teaser/f680869b-16f1-4507-a7a5-c30c41c9eaed?resourceVersion=id%3A923258"
          }
        },
        "resourceIdObjMeta": {
          "target_revision_id": 923258,
          "drupal_internal__target_id": 30081
        },
        "paragraph_type": {
          "type": "paragraphs_type--paragraphs_type",
          "id": "072db7a4-476e-41a6-ab49-c44184281451",
          "resourceIdObjMeta": {
            "drupal_internal__target_id": "link_teaser"
          }
        },
        "relationshipNames": ["paragraph_type"]
      },
      {
        "type": "paragraph--link_teaser",
        "id": "da804006-05fe-4aba-8146-8fdfeb229ca1",
        "drupal_internal__id": 30082,
        "drupal_internal__revision_id": 923259,
        "langcode": "en",
        "status": true,
        "created": "2021-03-02T14:37:28+00:00",
        "parent_id": "13881",
        "parent_type": "paragraph",
        "parent_field_name": "field_va_paragraphs",
        "behavior_settings": [],
        "default_langcode": true,
        "revision_translation_affected": true,
        "breadcrumbs": [],
        "content_translation_source": "und",
        "content_translation_outdated": false,
        "content_translation_changed": null,
        "field_link": {
          "uri": "https://www.visn2.va.gov/VISN2/index.asp",
          "title": "Read our annual reports and newsletters",
          "options": [],
          "url": "https://www.visn2.va.gov/VISN2/index.asp"
        },
        "field_link_summary": null,
        "links": {
          "self": {
            "href": "https://content-build-medc0xjkxm4jmpzxl3tfbcs7qcddsivh.ci.cms.va.gov/jsonapi/paragraph/link_teaser/da804006-05fe-4aba-8146-8fdfeb229ca1?resourceVersion=id%3A923259"
          }
        },
        "resourceIdObjMeta": {
          "target_revision_id": 923259,
          "drupal_internal__target_id": 30082
        },
        "paragraph_type": {
          "type": "paragraphs_type--paragraphs_type",
          "id": "072db7a4-476e-41a6-ab49-c44184281451",
          "resourceIdObjMeta": {
            "drupal_internal__target_id": "link_teaser"
          }
        },
        "relationshipNames": ["paragraph_type"]
      },
      {
        "type": "paragraph--link_teaser",
        "id": "83a66277-e72b-4224-b261-5a36659b0c68",
        "drupal_internal__id": 30083,
        "drupal_internal__revision_id": 923260,
        "langcode": "en",
        "status": true,
        "created": "2021-03-02T14:40:39+00:00",
        "parent_id": "13881",
        "parent_type": "paragraph",
        "parent_field_name": "field_va_paragraphs",
        "behavior_settings": [],
        "default_langcode": true,
        "revision_translation_affected": true,
        "breadcrumbs": [],
        "content_translation_source": "und",
        "content_translation_outdated": false,
        "content_translation_changed": null,
        "field_link": {
          "uri": "entity:node/9437",
          "title": "Compare our performance with non-VA facilities.",
          "options": [],
          "url": "/new-york-harbor-health-care/about-us/performance"
        },
        "field_link_summary": null,
        "links": {
          "self": {
            "href": "https://content-build-medc0xjkxm4jmpzxl3tfbcs7qcddsivh.ci.cms.va.gov/jsonapi/paragraph/link_teaser/83a66277-e72b-4224-b261-5a36659b0c68?resourceVersion=id%3A923260"
          }
        },
        "resourceIdObjMeta": {
          "target_revision_id": 923260,
          "drupal_internal__target_id": 30083
        },
        "paragraph_type": {
          "type": "paragraphs_type--paragraphs_type",
          "id": "072db7a4-476e-41a6-ab49-c44184281451",
          "resourceIdObjMeta": {
            "drupal_internal__target_id": "link_teaser"
          }
        },
        "relationshipNames": ["paragraph_type"]
      }
    ],
    "relationshipNames": ["paragraph_type", "field_va_paragraphs"]
  },
  "field_system_menu": {
    "type": "menu--menu",
    "id": "8c08ba3b-a738-42b0-b3b6-866d780697ce",
    "resourceIdObjMeta": {
      "drupal_internal__target_id": "va-new-york-harbor-health-care"
    }
  },
  "relationshipNames": [
    "node_type",
    "revision_uid",
    "uid",
    "field_administration",
    "field_clinical_health_services",
    "field_media",
    "field_related_links",
    "field_system_menu"
  ]
}
